odoo/addons/purchase_tier_validation/README.rst
odoo/addons/purchase_tier_validation/__init__.py
odoo/addons/purchase_tier_validation/__manifest__.py
odoo/addons/purchase_tier_validation/i18n/es.po
odoo/addons/purchase_tier_validation/i18n/purchase_tier_validation.pot
odoo/addons/purchase_tier_validation/i18n/zh_CN.po
odoo/addons/purchase_tier_validation/models/__init__.py
odoo/addons/purchase_tier_validation/models/purchase_order.py
odoo/addons/purchase_tier_validation/models/tier_definition.py
odoo/addons/purchase_tier_validation/static/description/icon.png
odoo/addons/purchase_tier_validation/views/purchase_order_view.xml
odoo12_addon_purchase_tier_validation-12.0.1.0.0.99.dev8.dist-info/METADATA
odoo12_addon_purchase_tier_validation-12.0.1.0.0.99.dev8.dist-info/WHEEL
odoo12_addon_purchase_tier_validation-12.0.1.0.0.99.dev8.dist-info/top_level.txt
odoo12_addon_purchase_tier_validation-12.0.1.0.0.99.dev8.dist-info/RECORD
